setup.py
punycodeurl/__init__.py
punycodeurl.egg-info/PKG-INFO
punycodeurl.egg-info/SOURCES.txt
punycodeurl.egg-info/dependency_links.txt
punycodeurl.egg-info/top_level.txt