Metadata-Version: 1.0
Name: punycodeurl
Version: 0.1
Summary: punycodeurl for Url
Home-page: https://github.com/charsyam/punycodeurl
Author: DaeMyung Kang
Author-email: charsyam@gmail.com
License: UNKNOWN
Platform: any
